LICENSE
MANIFEST.in
README.md
setup.cfg
setup.py
django_gtin_fields.egg-info/PKG-INFO
django_gtin_fields.egg-info/SOURCES.txt
django_gtin_fields.egg-info/dependency_links.txt
django_gtin_fields.egg-info/not-zip-safe
django_gtin_fields.egg-info/requires.txt
django_gtin_fields.egg-info/top_level.txt
gtin_fields/__init__.py
gtin_fields/converters.py
gtin_fields/fields.py
gtin_fields/gtin.py
gtin_fields/models.py
gtin_fields/urls.py
gtin_fields/validators.py