Metadata-Version: 1.1
Name: django-gtin-fields
Version: 0.1.0
Summary: Provides model fields and validation for GTIN codes (EAN, UPC, GTIN, ISBN)
Home-page: https://github.com/DobaTech/django-gtin-fields
Author: John T. Prince, under employ of Doba Inc.
Author-email: jtprince@doba.com, jtprince@gmail.com
License: LPGL
Keywords: django,gtin,upc,ean,isbn,model,fieldUPC-A,UPC-E,EAN-13,GTIN-14,ASIN,Amazon Standard Identification Number
Platform: UNKNOWN
Classifier: Topic :: Utilities
Classifier: Natural Language :: English
Classifier: Operating System :: OS Independent
Classifier: Intended Audience :: Developers
Classifier: Environment :: Web Environment
Classifier: Framework :: Django
Classifier: License :: OSI Approved :: GNU Lesser General Public License v3 (LGPLv3)
Classifier: Development Status :: 5 - Production/Stable
Classifier: Programming Language :: Python
Classifier: Programming Language :: Python :: 3
